blocklister/__init__.py
blocklister/cli.py
blocklister/py.typed
blocklister-0.0.0.dist-info/METADATA
blocklister-0.0.0.dist-info/WHEEL
blocklister-0.0.0.dist-info/entry_points.txt
blocklister-0.0.0.dist-info/licenses/LICENSES/AGPL-3.0-or-later.md
blocklister-0.0.0.dist-info/licenses/LICENSES/CC0-1.0.txt
blocklister-0.0.0.dist-info/RECORD
