Metadata-Version: 2.4
Name: blocklister
Version: 0.0.0
Summary: Parse and output blocklists in various formats
Project-URL: Homepage, https://codeberg.org/Freso/python-blocklister
Project-URL: Issues, https://codeberg.org/Freso/python-blocklister/issues
Project-URL: Repository, https://codeberg.org/Freso/python-blocklister.git
Author: Frederik “Freso” S. Olesen
License-Expression: AGPL-3.0-or-later
License-File: LICENSES/AGPL-3.0-or-later.md
License-File: LICENSES/CC0-1.0.txt
Keywords: DNS,blocklists,hosts
Classifier: Development Status :: 1 - Planning
Classifier: Environment :: Console
Classifier: Intended Audience :: Developers
Classifier: Intended Audience :: System Administrators
Classifier: License :: OSI Approved :: GNU Affero General Public License v3 or later (AGPLv3+)
Classifier: Natural Language :: English
Classifier: Operating System :: OS Independent
Classifier: Programming Language :: Python :: 3
Classifier: Programming Language :: Python :: 3 :: Only
Classifier: Programming Language :: Python :: 3.10
Classifier: Programming Language :: Python :: 3.11
Classifier: Programming Language :: Python :: 3.12
Classifier: Programming Language :: Python :: 3.13
Classifier: Programming Language :: Python :: 3.14
Classifier: Programming Language :: Python :: 3.15
Classifier: Topic :: File Formats
Classifier: Topic :: Internet
Classifier: Topic :: Internet :: Name Service (DNS)
Classifier: Topic :: Security
Classifier: Topic :: Software Development :: Libraries :: Python Modules
Classifier: Topic :: System :: Networking
Classifier: Topic :: System :: Networking :: Firewalls
Classifier: Topic :: System :: Systems Administration
Classifier: Topic :: Utilities
Classifier: Typing :: Typed
Requires-Python: >=3.10
